client/__init__.py
client/client.py
client/client/__init__.py
client/client/add_contact.py
client/client/database.py
client/client/del_contact.py
client/client/main_window.py
client/client/main_window_conv.py
client/client/start_dialog.py
client/client/transport.py
client/common/__init__.py
client/common/decos.py
client/common/descryptors.py
client/common/errors.py
client/common/metaclasses.py
client/common/utils.py
client/common/variables.py
client/doc/__init__.py
client/doc/source/__init__.py
client/doc/source/conf.py
client/logs/__init__.py
client/logs/config_client_log.py
client/logs/config_server_log.py
client/unit_tests/__init__.py
client/unit_tests/test_client.py
client/unit_tests/test_server.py
client/unit_tests/test_utils.py
small_py_mess_client-0.5.1.dist-info/METADATA
small_py_mess_client-0.5.1.dist-info/WHEEL
small_py_mess_client-0.5.1.dist-info/top_level.txt
small_py_mess_client-0.5.1.dist-info/RECORD
