Metadata-Version: 2.1
Name: small-py-mess-client
Version: 0.5.1
Summary: mess_server
Author: Tankred
License: UNKNOWN
Platform: UNKNOWN
Requires-Dist: PyQt5
Requires-Dist: sqlalchemy
Requires-Dist: pycryptodome
Requires-Dist: pycryptodomex
